[
    {"county":"Adair County","fips_id":"21001","latitude":37.1099,"longitude":-85.2817},
    {"county":"Allen County","fips_id":"21003","latitude":36.7495,"longitude":-86.1905},
    {"county":"Anderson County","fips_id":"21005","latitude":38.0034,"longitude":-84.9897},
    {"county":"Ballard County","fips_id":"21007","latitude":37.0372,"longitude":-89.0436},
    {"county":"Barren County","fips_id":"21009","latitude":36.9931,"longitude":-85.9329},
    {"county":"Bath County","fips_id":"21011","latitude":38.1409,"longitude":-83.753},
    {"county":"Bell County","fips_id":"21013","latitude":36.7337,"longitude":-83.6756},
    {"county":"Boone County","fips_id":"21015","latitude":38.9723,"longitude":-84.7425},
    {"county":"Bourbon County","fips_id":"21017","latitude":38.2016,"longitude":-84.2268},
    {"county":"Boyd County","fips_id":"21019","latitude":38.3411,"longitude":-82.6881},
    {"county":"Boyle County","fips_id":"21021","latitude":37.6213,"longitude":-84.8715},
    {"county":"Bracken County","fips_id":"21023","latitude":38.6704,"longitude":-84.0857},
    {"county":"Breathitt County","fips_id":"21025","latitude":37.5329,"longitude":-83.319},
    {"county":"Breckinridge County","fips_id":"21027","latitude":37.7736,"longitude":-86.4549},
    {"county":"Bullitt County","fips_id":"21029","latitude":37.9921,"longitude":-85.6718},
    {"county":"Butler County","fips_id":"21031","latitude":37.2093,"longitude":-86.685},
    {"county":"Caldwell County","fips_id":"21033","latitude":37.1547,"longitude":-87.8695},
    {"county":"Calloway County","fips_id":"21035","latitude":36.6211,"longitude":-88.2971},
    {"county":"Campbell County","fips_id":"21037","latitude":38.9391,"longitude":-84.3963},
    {"county":"Carlisle County","fips_id":"21039","latitude":36.8572,"longitude":-88.991},
    {"county":"Carroll County","fips_id":"21041","latitude":38.6806,"longitude":-85.153},
    {"county":"Carter County","fips_id":"21043","latitude":38.3287,"longitude":-83.0731},
    {"county":"Casey County","fips_id":"21045","latitude":37.3333,"longitude":-84.9264},
    {"county":"Christian County","fips_id":"21047","latitude":36.8694,"longitude":-87.4886},
    {"county":"Clark County","fips_id":"21049","latitude":37.9941,"longitude":-84.1469},
    {"county":"Clay County","fips_id":"21051","latitude":37.1583,"longitude":-83.7233},
    {"county":"Clinton County","fips_id":"21053","latitude":36.7276,"longitude":-85.1333},
    {"county":"Crittenden County","fips_id":"21055","latitude":37.3421,"longitude":-88.1047},
    {"county":"Cumberland County","fips_id":"21057","latitude":36.7891,"longitude":-85.4085},
    {"county":"Daviess County","fips_id":"21059","latitude":37.7336,"longitude":-87.1348},
    {"county":"Edmonson County","fips_id":"21061","latitude":37.2185,"longitude":-86.2636},
    {"county":"Elliott County","fips_id":"21063","latitude":38.0855,"longitude":-83.1125},
    {"county":"Estill County","fips_id":"21065","latitude":37.6758,"longitude":-83.9423},
    {"county":"Fayette County","fips_id":"21067","latitude":38.0343,"longitude":-84.5001},
    {"county":"Fleming County","fips_id":"21069","latitude":38.3591,"longitude":-83.6744},
    {"county":"Floyd County","fips_id":"21071","latitude":37.5482,"longitude":-82.7502},
    {"county":"Franklin County","fips_id":"21073","latitude":38.2202,"longitude":-84.8663},
    {"county":"Fulton County","fips_id":"21075","latitude":36.5202,"longitude":-89.2037},
    {"county":"Gallatin County","fips_id":"21077","latitude":38.7631,"longitude":-84.9133},
    {"county":"Garrard County","fips_id":"21079","latitude":37.6348,"longitude":-84.5792},
    {"county":"Grant County","fips_id":"21081","latitude":38.6407,"longitude":-84.6199},
    {"county":"Graves County","fips_id":"21083","latitude":36.7244,"longitude":-88.6336},
    {"county":"Grayson County","fips_id":"21085","latitude":37.4686,"longitude":-86.3331},
    {"county":"Green County","fips_id":"21087","latitude":37.2859,"longitude":-85.4809},
    {"county":"Greenup County","fips_id":"21089","latitude":38.5436,"longitude":-82.9337},
    {"county":"Hancock County","fips_id":"21091","latitude":37.8326,"longitude":-86.7671},
    {"county":"Hardin County","fips_id":"21093","latitude":37.6979,"longitude":-85.963},
    {"county":"Harlan County","fips_id":"21095","latitude":36.8698,"longitude":-83.2214},
    {"county":"Harrison County","fips_id":"21097","latitude":38.4339,"longitude":-84.3058},
    {"county":"Hart County","fips_id":"21099","latitude":37.2939,"longitude":-85.8894},
    {"county":"Henderson County","fips_id":"21101","latitude":37.8124,"longitude":-87.5811},
    {"county":"Henry County","fips_id":"21103","latitude":38.4398,"longitude":-85.0454},
    {"county":"Hickman County","fips_id":"21105","latitude":36.6484,"longitude":-88.9401},
    {"county":"Hopkins County","fips_id":"21107","latitude":37.3188,"longitude":-87.5664},
    {"county":"Jackson County","fips_id":"21109","latitude":37.4382,"longitude":-84.0963},
    {"county":"Jefferson County","fips_id":"21111","latitude":38.1809,"longitude":-85.6746},
    {"county":"Jessamine County","fips_id":"21113","latitude":37.8606,"longitude":-84.5789},
    {"county":"Johnson County","fips_id":"21115","latitude":37.8341,"longitude":-82.8347},
    {"county":"Kenton County","fips_id":"21117","latitude":38.9463,"longitude":-84.5387},
    {"county":"Knott County","fips_id":"21119","latitude":37.3561,"longitude":-82.943},
    {"county":"Knox County","fips_id":"21121","latitude":36.8897,"longitude":-83.8847},
    {"county":"Larue County","fips_id":"21123","latitude":37.5677,"longitude":-85.7165},
    {"county":"Laurel County","fips_id":"21125","latitude":37.1108,"longitude":-84.1046},
    {"county":"Lawrence County","fips_id":"21127","latitude":38.0613,"longitude":-82.7346},
    {"county":"Lee County","fips_id":"21129","latitude":37.5838,"longitude":-83.7151},
    {"county":"Leslie County","fips_id":"21131","latitude":37.0847,"longitude":-83.3725},
    {"county":"Letcher County","fips_id":"21133","latitude":37.1205,"longitude":-82.8339},
    {"county":"Lewis County","fips_id":"21135","latitude":38.5458,"longitude":-83.345},
    {"county":"Lincoln County","fips_id":"21137","latitude":37.4595,"longitude":-84.637},
    {"county":"Livingston County","fips_id":"21139","latitude":37.2199,"longitude":-88.3493},
    {"county":"Logan County","fips_id":"21141","latitude":36.8496,"longitude":-86.8919},
    {"county":"Lyon County","fips_id":"21143","latitude":37.0251,"longitude":-88.081},
    {"county":"McCracken County","fips_id":"21145","latitude":37.0726,"longitude":-88.7074},
    {"county":"McCreary County","fips_id":"21147","latitude":36.7403,"longitude":-84.4977},
    {"county":"McLean County","fips_id":"21149","latitude":37.5235,"longitude":-87.2685},
    {"county":"Madison County","fips_id":"21151","latitude":37.7119,"longitude":-84.2697},
    {"county":"Magoffin County","fips_id":"21153","latitude":37.7279,"longitude":-83.0706},
    {"county":"Marion County","fips_id":"21155","latitude":37.5867,"longitude":-85.2529},
    {"county":"Marshall County","fips_id":"21157","latitude":36.8367,"longitude":-88.2984},
    {"county":"Martin County","fips_id":"21159","latitude":37.8093,"longitude":-82.512},
    {"county":"Mason County","fips_id":"21161","latitude":38.6191,"longitude":-83.8323},
    {"county":"Meade County","fips_id":"21163","latitude":37.9654,"longitude":-86.2351},
    {"county":"Menifee County","fips_id":"21165","latitude":37.9344,"longitude":-83.619},
    {"county":"Mercer County","fips_id":"21167","latitude":37.7806,"longitude":-84.8687},
    {"county":"Metcalfe County","fips_id":"21169","latitude":36.9735,"longitude":-85.6299},
    {"county":"Monroe County","fips_id":"21171","latitude":36.7268,"longitude":-85.7213},
    {"county":"Montgomery County","fips_id":"21173","latitude":38.0364,"longitude":-83.9206},
    {"county":"Morgan County","fips_id":"21175","latitude":37.9256,"longitude":-83.2914},
    {"county":"Muhlenberg County","fips_id":"21177","latitude":37.2272,"longitude":-87.1435},
    {"county":"Nelson County","fips_id":"21179","latitude":37.8,"longitude":-85.4652},
    {"county":"Nicholas County","fips_id":"21181","latitude":38.3571,"longitude":-84.0128},
    {"county":"Ohio County","fips_id":"21183","latitude":37.4443,"longitude":-86.8546},
    {"county":"Oldham County","fips_id":"21185","latitude":38.3957,"longitude":-85.4592},
    {"county":"Owen County","fips_id":"21187","latitude":38.5335,"longitude":-84.8395},
    {"county":"Owsley County","fips_id":"21189","latitude":37.4254,"longitude":-83.6881},
    {"county":"Pendleton County","fips_id":"21191","latitude":38.7028,"longitude":-84.3853},
    {"county":"Perry County","fips_id":"21193","latitude":37.2871,"longitude":-83.211},
    {"county":"Pike County","fips_id":"21195","latitude":37.4774,"longitude":-82.4081},
    {"county":"Powell County","fips_id":"21197","latitude":37.8258,"longitude":-83.8303},
    {"county":"Pulaski County","fips_id":"21199","latitude":37.0948,"longitude":-84.5743},
    {"county":"Robertson County","fips_id":"21201","latitude":38.5204,"longitude":-84.0782},
    {"county":"Rockcastle County","fips_id":"21203","latitude":37.3728,"longitude":-84.3216},
    {"county":"Rowan County","fips_id":"21205","latitude":38.1919,"longitude":-83.4688},
    {"county":"Russell County","fips_id":"21207","latitude":36.9929,"longitude":-85.0659},
    {"county":"Scott County","fips_id":"21209","latitude":38.2965,"longitude":-84.591},
    {"county":"Shelby County","fips_id":"21211","latitude":38.2183,"longitude":-85.2232},
    {"county":"Simpson County","fips_id":"21213","latitude":36.7462,"longitude":-86.5823},
    {"county":"Spencer County","fips_id":"21215","latitude":38.0134,"longitude":-85.308},
    {"county":"Taylor County","fips_id":"21217","latitude":37.3396,"longitude":-85.3348},
    {"county":"Todd County","fips_id":"21219","latitude":36.8388,"longitude":-87.168},
    {"county":"Trigg County","fips_id":"21221","latitude":36.7949,"longitude":-87.8766},
    {"county":"Trimble County","fips_id":"21223","latitude":38.6125,"longitude":-85.344},
    {"county":"Union County","fips_id":"21225","latitude":37.6739,"longitude":-87.9307},
    {"county":"Warren County","fips_id":"21227","latitude":36.9833,"longitude":-86.4457},
    {"county":"Washington County","fips_id":"21229","latitude":37.7512,"longitude":-85.167},
    {"county":"Wayne County","fips_id":"21231","latitude":36.8038,"longitude":-84.8269},
    {"county":"Webster County","fips_id":"21233","latitude":37.5482,"longitude":-87.6791},
    {"county":"Whitley County","fips_id":"21235","latitude":36.8274,"longitude":-84.2171},
    {"county":"Wolfe County","fips_id":"21237","latitude":37.7417,"longitude":-83.498},
    {"county":"Woodford County","fips_id":"21239","latitude":38.0328,"longitude":-84.7357}
]
